kspalculator
