Metadata-Version: 1.1
Name: kspalculator
Version: 0.10.2
Summary: Determine the best rocket propulsion designs for one stage of a rocket, given a set of constraints and preferences (Kerbal Space Program).
Home-page: https://github.com/aandergr/kspalculator
Author: Alexander Graf, André Koch-Kramer
Author-email: mail@agraf.me, koch-kramer@web.de
License: MIT
Keywords: ksp kerbal space program kerbalspaceprogram calculator calculate optimize engine fuel propellant
Platform: UNKNOWN
Classifier: Development Status :: 4 - Beta
Classifier: Environment :: Console
Classifier: Intended Audience :: End Users/Desktop
Classifier: License :: OSI Approved :: MIT License
Classifier: Operating System :: OS Independent
Classifier: Programming Language :: Python :: 3.4
Classifier: Programming Language :: Python :: 3.5
Classifier: Programming Language :: Python :: 3.6
Classifier: Programming Language :: Python :: 3 :: Only
